nested_csv/__init__.py
nested_csv/writer.py
nested_csv-0.1.0.dist-info/LICENSE
nested_csv-0.1.0.dist-info/METADATA
nested_csv-0.1.0.dist-info/WHEEL
nested_csv-0.1.0.dist-info/top_level.txt
nested_csv-0.1.0.dist-info/RECORD
