Metadata-Version: 2.1
Name: nested-csv
Version: 0.1.0
Summary: CSV generator for nested dict or list data structure such asJSON
Home-page: https://github.com/kawasin73/nested_csv
Author: Kawamura Shintaro
Author-email: kawasin73@gmail.com
License: UNKNOWN
Platform: UNKNOWN
Classifier: Programming Language :: Python :: 3
Classifier: License :: OSI Approved :: MIT License
Classifier: Operating System :: OS Independent
Requires-Python: >=3.6
